odoo10_addon_event_registration_multi_qty-10.0.1.0.0.99.dev4-py2.7-nspkg.pth
odoo/addons/event_registration_multi_qty/README.rst
odoo/addons/event_registration_multi_qty/__init__.py
odoo/addons/event_registration_multi_qty/__manifest__.py
odoo/addons/event_registration_multi_qty/i18n/es.po
odoo/addons/event_registration_multi_qty/i18n/event_registration_multi_qty.pot
odoo/addons/event_registration_multi_qty/models/__init__.py
odoo/addons/event_registration_multi_qty/models/event.py
odoo/addons/event_registration_multi_qty/reports/__init__.py
odoo/addons/event_registration_multi_qty/reports/report_event_registration.py
odoo/addons/event_registration_multi_qty/static/description/icon.png
odoo/addons/event_registration_multi_qty/tests/__init__.py
odoo/addons/event_registration_multi_qty/tests/test_event_registration_multi_qty.py
odoo/addons/event_registration_multi_qty/views/event_view.xml
odoo10_addon_event_registration_multi_qty-10.0.1.0.0.99.dev4.dist-info/METADATA
odoo10_addon_event_registration_multi_qty-10.0.1.0.0.99.dev4.dist-info/RECORD
odoo10_addon_event_registration_multi_qty-10.0.1.0.0.99.dev4.dist-info/WHEEL
odoo10_addon_event_registration_multi_qty-10.0.1.0.0.99.dev4.dist-info/namespace_packages.txt
odoo10_addon_event_registration_multi_qty-10.0.1.0.0.99.dev4.dist-info/top_level.txt
